dattos_data_engine_common/__init__.py
dattos_data_engine_common-15.0.15.dist-info/licenses/LICENSE
dattos_data_engine_common-15.0.15.dist-info/METADATA
dattos_data_engine_common-15.0.15.dist-info/WHEEL
dattos_data_engine_common-15.0.15.dist-info/top_level.txt
dattos_data_engine_common-15.0.15.dist-info/RECORD
