Metadata-Version: 2.4
Name: dattos_data_engine_common
Version: 15.0.15
Summary: Common classes and methods for data engine projects
Author-email: Matheus Gaspar <matheus.oliveira@dattos.com.br>
License-Expression: MIT
Project-URL: Homepage, https://dattos.com.br
Classifier: Programming Language :: Python :: 3
Classifier: Operating System :: OS Independent
Requires-Python: >=3.8
License-File: LICENSE
Provides-Extra: dev
Requires-Dist: pandas; extra == "dev"
Requires-Dist: bumpver; extra == "dev"
Requires-Dist: twine; extra == "dev"
Requires-Dist: wheel; extra == "dev"
Requires-Dist: build; extra == "dev"
Requires-Dist: adlfs; extra == "dev"
Requires-Dist: s3fs; extra == "dev"
Requires-Dist: gcsfs; extra == "dev"
Requires-Dist: pydantic; extra == "dev"
Requires-Dist: structlog; extra == "dev"
Provides-Extra: docs
Requires-Dist: sphinx; extra == "docs"
Requires-Dist: furo; extra == "docs"
Dynamic: license-file
